cwe/__init__.py
cwe/categories.py
cwe/category_index.json
cwe/database.py
cwe/db.pickle.gz
cwe/mappings.py
cwe/weakness.py
tests/__init__.py
tests/test_cwe.py
cwe-1.6.dist-info/LICENSE.txt
cwe-1.6.dist-info/METADATA
cwe-1.6.dist-info/WHEEL
cwe-1.6.dist-info/top_level.txt
cwe-1.6.dist-info/RECORD
