Metadata-Version: 2.1
Name: cwe
Version: 1.6
Summary: Common weakness enumeration wrapper for Python
Home-page: https://github.com/Julian-Nash/cwe
Author: Julian Nash
Author-email: julianjamesnash@gmail.com
License: UNKNOWN
Project-URL: Bug Tracker, https://github.com/Julian-Nash/cwe
Project-URL: Documentation, https://github.com/Julian-Nash/cwe
Project-URL: Source Code, https://github.com/Julian-Nash/cwe
Keywords: python example
Platform: UNKNOWN
Classifier: Intended Audience :: Developers
Classifier: License :: OSI Approved :: MIT License
Classifier: Programming Language :: Python :: 3.6
Classifier: Programming Language :: Python :: 3.7
Classifier: Programming Language :: Python :: 3.8
